{
  "results": [
    {
      "@id": "http://www.bbc.co.uk/things/e340df4c-c1d8-4c42-aacb-3a8b54272397#id",
      "@type": [
        "CreativeWork",
        "NewsItem"
      ],
      "dateCreated": "2019-11-06T00:11:07+00:00",
      "dateModified": "2019-11-06T00:11:07+00:00",
      "description": "La Conmebol decidió trasladar a Lima la final de la Copa Libertadores por la ola de protestas que vive Chile.",
      "shortTitle": "La final de la Copa Libertadores se traslada a Lima por las protestas en Chile",
      "title": "Copa Libertadores: las protestas en Chile obligan a trasladar a Lima la final entre River Plate y Flamengo",
      "category": "http://www.bbc.co.uk/ontologies/applicationlogic-news/News",
      "locator": [
        "urn:asset:8ee27645-56cb-9340-92c4-549787d71804",
        "urn:bbc:cps:asset:50311930"
      ],
      "primaryFormat": "TextualFormat",
      "about": [
        {
          "@id": "http://www.bbc.co.uk/things/03ef2794-4827-470e-b6dd-eec233217405#id",
          "@type": [
            "Thing",
            "Place",
            "geoname:GeoTagConcept"
          ],
          "label": "Peru",
          "preferredLabel": "Peru",
          "sameAs": "http://sws.geonames.org/3932488/"
        },
        {
          "@id": "http://www.bbc.co.uk/things/15f1bcf6-b6ab-48e8-b708-efed41e43d31#id",
          "@type": [
            "Thing",
            "Place",
            "geoname:GeoTagConcept"
          ],
          "label": "Brazil",
          "preferredLabel": "Brazil",
          "slug": "Brazil",
          "sameAs": "http://sws.geonames.org/3469034/"
        },
        {
          "@id": "http://www.bbc.co.uk/things/4063f80f-cccc-44c8-9449-5ca44e4c8592#id",
          "@type": [
            "http://data.press.net/ontology/classification/Classification",
            "http://www.bbc.co.uk/ontologies/classification/RootClassification",
            "skos:Concept",
            "Thing",
            "Theme"
          ],
          "label": "Sport",
          "preferredLabel": "Sport",
          "shortLabel": "Sport",
          "slug": "sport",
          "primaryTopicOf": [
            "http://en.wikipedia.org/wiki/Sport",
            "http://www.bbc.co.uk/sport"
          ],
          "sameAs": "http://dbpedia.org/resource/Sport"
        },
        {
          "@id": "http://www.bbc.co.uk/things/6b71918f-e3a3-4dff-ad36-c3d737605d43#id",
          "@type": [
            "Thing",
            "sport:RecurringCompetition",
            "sport:Competition"
          ],
          "label": "Copa Libertadores",
          "preferredLabel": "Copa Libertadores",
          "shortLabel": "Copa Libertadores",
          "slug": "copa-libertadores",
          "sameAs": "http://dbpedia.org/resource/Copa_Libertadores",
          "primaryTopicOf": [
            {
              "@id": "http://www.bbc.co.uk/sport/football/copa-libertadores",
              "webDocumentCategory": "http://www.bbc.co.uk/ontologies/applicationlogic-sport/Index"
            }
          ]
        },
        {
          "@id": "http://www.bbc.co.uk/things/b67450e8-ed1d-434b-b01b-8aa7e159381e#id",
          "@type": [
            "Thing",
            "Place",
            "geoname:GeoTagConcept"
          ],
          "label": "Chile",
          "preferredLabel": "Chile",
          "sameAs": "http://sws.geonames.org/3895114/"
        },
        {
          "@id": "http://www.bbc.co.uk/things/ba6e1118-f874-054e-b159-b797c16e9250#id",
          "@type": [
            "Thing",
            "sport:SportsDiscipline",
            "http://www.bbc.co.uk/ontologies/applicationlogic-sport/SportTopic",
            "Theme"
          ],
          "label": [
            "Football",
            "Football"
          ],
          "preferredLabel": "Football",
          "shortLabel": "Football",
          "slug": "football",
          "primaryTopicOf": [
            "http://en.wikipedia.org/wiki/Association_football",
            "http://www.bbc.co.uk/sport/football",
            "http://www.fifa.com/",
            {
              "@id": "http://www.faw.org.uk/",
              "webDocumentCategory": "http://www.bbc.co.uk/ontologies/applicationlogic-sport/ExternalWebsite"
            },
            {
              "@id": "http://www.irishfa.com/",
              "webDocumentCategory": "http://www.bbc.co.uk/ontologies/applicationlogic-sport/ExternalWebsite"
            },
            {
              "@id": "http://www.scottishfa.co.uk/",
              "webDocumentCategory": "http://www.bbc.co.uk/ontologies/applicationlogic-sport/ExternalWebsite"
            },
            {
              "@id": "http://www.thefa.com/",
              "webDocumentCategory": "http://www.bbc.co.uk/ontologies/applicationlogic-sport/ExternalWebsite"
            }
          ],
          "sameAs": "http://dbpedia.org/resource/Association_football"
        },
        {
          "@id": "http://www.bbc.co.uk/things/f0e68d01-22ae-42a7-9e05-d299a29d4ce5#id",
          "@type": [
            "Thing",
            "Place",
            "geoname:GeoTagConcept"
          ],
          "label": "Argentina",
          "preferredLabel": "Argentina",
          "sameAs": "http://sws.geonames.org/3865483/"
        }
      ],
      "primaryContentOf": [
        {
          "@id": "http://www.bbc.co.uk/mundo/deportes-50311930",
          "platform": "HighWeb",
          "webDocumentType": "HighWeb"
        }
      ],
      "thumbnail": [
        {
          "@id": "http://c.files.bbci.co.uk/121FA/production/_109543247_b3198eb8-4f22-41f8-bece-b64cd8fcedf8.jpg",
          "@type": [
            "Thumbnail"
          ],
          "altText": "Conmebol",
          "thumbnailType": "StandardThumbnail"
        }
      ]
    },
    {
      "@id": "http://www.bbc.co.uk/things/2c7e207a-dc06-452d-a465-5d36fbb02749#id",
      "@type": [
        "NewsItem",
        "CreativeWork"
      ],
      "dateCreated": "2019-10-24T08:38:01+00:00",
      "dateModified": "2019-10-24T08:38:01+00:00",
      "description": "Flamengo reach their first Copa Libertadores final in 35 years after thrashing fellow Brazilian side Gremio 5-0 in their semi-final second leg.",
      "shortTitle": "Flamengo beat Gremio to reach final",
      "title": "Copa Libertadores: Flamengo beat Gremio and face River Plate in final",
      "category": "http://www.bbc.co.uk/ontologies/applicationlogic-sport/News",
      "locator": [
        "urn:asset:6608cab2-520c-194f-a970-5ae5f0c023ea",
        "urn:bbc:cps:asset:50166368"
      ],
      "primaryFormat": "TextualFormat",
      "about": [
        {
          "@id": "http://www.bbc.co.uk/things/0350ec6a-76af-4d2b-80f5-396998ce775b#id",
          "@type": [
            "Thing",
            "http://www.bbc.co.uk/ontologies/event/RecurringEvent",
            "sport:RecurringCompetition",
            "http://www.bbc.co.uk/ontologies/applicationlogic-sport/SportTopic",
            "sport:Competition"
          ],
          "label": "Brazilian Série A",
          "preferredLabel": "Brazilian Série A",
          "shortLabel": "Brazilian Série A",
          "slug": "brazilian-league",
          "primaryTopicOf": [
            {
              "@id": "http://www.bbc.co.uk/sport/football/brazilian-league",
              "webDocumentCategory": "http://www.bbc.co.uk/ontologies/applicationlogic-sport/Index"
            }
          ]
        },
        {
          "@id": "http://www.bbc.co.uk/things/1cfe0e12-c314-4427-9d69-8342d145a1b1#id",
          "@type": [
            "Thing",
            "Place",
            "geoname:GeoTagConcept"
          ],
          "label": "Rio de Janeiro",
          "preferredLabel": "Rio de Janeiro",
          "sameAs": "http://sws.geonames.org/3451190/"
        },
        {
          "@id": "http://www.bbc.co.uk/things/4063f80f-cccc-44c8-9449-5ca44e4c8592#id",
          "@type": [
            "http://data.press.net/ontology/classification/Classification",
            "http://www.bbc.co.uk/ontologies/classification/RootClassification",
            "skos:Concept",
            "Thing",
            "Theme"
          ],
          "label": "Sport",
          "preferredLabel": "Sport",
          "shortLabel": "Sport",
          "slug": "sport",
          "primaryTopicOf": [
            "http://en.wikipedia.org/wiki/Sport",
            "http://www.bbc.co.uk/sport"
          ],
          "sameAs": "http://dbpedia.org/resource/Sport"
        },
        {
          "@id": "http://www.bbc.co.uk/things/6b71918f-e3a3-4dff-ad36-c3d737605d43#id",
          "@type": [
            "Thing",
            "sport:RecurringCompetition",
            "sport:Competition"
          ],
          "label": "Copa Libertadores",
          "preferredLabel": "Copa Libertadores",
          "shortLabel": "Copa Libertadores",
          "slug": "copa-libertadores",
          "sameAs": "http://dbpedia.org/resource/Copa_Libertadores",
          "primaryTopicOf": [
            {
              "@id": "http://www.bbc.co.uk/sport/football/copa-libertadores",
              "webDocumentCategory": "http://www.bbc.co.uk/ontologies/applicationlogic-sport/Index"
            }
          ]
        },
        {
          "@id": "http://www.bbc.co.uk/things/ba6e1118-f874-054e-b159-b797c16e9250#id",
          "@type": [
            "Thing",
            "sport:SportsDiscipline",
            "http://www.bbc.co.uk/ontologies/applicationlogic-sport/SportTopic",
            "Theme"
          ],
          "label": [
            "Football",
            "Football"
          ],
          "preferredLabel": "Football",
          "shortLabel": "Football",
          "slug": "football",
          "primaryTopicOf": [
            "http://en.wikipedia.org/wiki/Association_football",
            "http://www.bbc.co.uk/sport/football",
            "http://www.fifa.com/",
            {
              "@id": "http://www.faw.org.uk/",
              "webDocumentCategory": "http://www.bbc.co.uk/ontologies/applicationlogic-sport/ExternalWebsite"
            },
            {
              "@id": "http://www.irishfa.com/",
              "webDocumentCategory": "http://www.bbc.co.uk/ontologies/applicationlogic-sport/ExternalWebsite"
            },
            {
              "@id": "http://www.scottishfa.co.uk/",
              "webDocumentCategory": "http://www.bbc.co.uk/ontologies/applicationlogic-sport/ExternalWebsite"
            },
            {
              "@id": "http://www.thefa.com/",
              "webDocumentCategory": "http://www.bbc.co.uk/ontologies/applicationlogic-sport/ExternalWebsite"
            }
          ],
          "sameAs": "http://dbpedia.org/resource/Association_football"
        }
      ],
      "primaryContentOf": [
        {
          "@id": "http://www.bbc.co.uk/sport/football/50166368",
          "platform": "HighWeb",
          "webDocumentType": "HighWeb"
        }
      ],
      "thumbnail": [
        {
          "@id": "http://c.files.bbci.co.uk/FC03/production/_109351546_gettyimages-1183016837.jpg",
          "@type": [
            "Thumbnail"
          ],
          "altText": "Flamengo players celebrate at the final whistle after beating Gremio to reach the Copa Libertadores final",
          "thumbnailType": "StandardThumbnail"
        }
      ]
    },
    {
      "@id": "http://www.bbc.co.uk/things/e8ad34de-ccd7-46da-940a-6e78be4e5723#id",
      "@type": [
        "CreativeWork",
        "NewsItem"
      ],
      "dateCreated": "2019-10-23T06:23:29+00:00",
      "dateModified": "2019-10-23T06:23:29+00:00",
      "description": "Defending champions River Plate reach the Copa Libertadores final with a 2-1 win on aggregate in the semi-final against city rivals Boca Juniors.",
      "shortTitle": "River Plate lose to Boca but reach final",
      "title": "Copa Libertadores: River Plate lose to Boca Juniors but reach final",
      "category": "http://www.bbc.co.uk/ontologies/applicationlogic-sport/News",
      "locator": [
        "urn:asset:8c1e03e9-09d5-6040-9c94-81bba8b8fca0",
        "urn:bbc:cps:asset:50149823"
      ],
      "primaryFormat": "TextualFormat",
      "about": [
        {
          "@id": "http://www.bbc.co.uk/things/4063f80f-cccc-44c8-9449-5ca44e4c8592#id",
          "@type": [
            "http://data.press.net/ontology/classification/Classification",
            "http://www.bbc.co.uk/ontologies/classification/RootClassification",
            "skos:Concept",
            "Thing",
            "Theme"
          ],
          "label": "Sport",
          "preferredLabel": "Sport",
          "shortLabel": "Sport",
          "slug": "sport",
          "primaryTopicOf": [
            "http://en.wikipedia.org/wiki/Sport",
            "http://www.bbc.co.uk/sport"
          ],
          "sameAs": "http://dbpedia.org/resource/Sport"
        },
        {
          "@id": "http://www.bbc.co.uk/things/6b71918f-e3a3-4dff-ad36-c3d737605d43#id",
          "@type": [
            "Thing",
            "sport:RecurringCompetition",
            "sport:Competition"
          ],
          "label": "Copa Libertadores",
          "preferredLabel": "Copa Libertadores",
          "shortLabel": "Copa Libertadores",
          "slug": "copa-libertadores",
          "sameAs": "http://dbpedia.org/resource/Copa_Libertadores",
          "primaryTopicOf": [
            {
              "@id": "http://www.bbc.co.uk/sport/football/copa-libertadores",
              "webDocumentCategory": "http://www.bbc.co.uk/ontologies/applicationlogic-sport/Index"
            }
          ]
        },
        {
          "@id": "http://www.bbc.co.uk/things/ba6e1118-f874-054e-b159-b797c16e9250#id",
          "@type": [
            "Thing",
            "sport:SportsDiscipline",
            "http://www.bbc.co.uk/ontologies/applicationlogic-sport/SportTopic",
            "Theme"
          ],
          "label": [
            "Football",
            "Football"
          ],
          "preferredLabel": "Football",
          "shortLabel": "Football",
          "slug": "football",
          "primaryTopicOf": [
            "http://en.wikipedia.org/wiki/Association_football",
            "http://www.bbc.co.uk/sport/football",
            "http://www.fifa.com/",
            {
              "@id": "http://www.faw.org.uk/",
              "webDocumentCategory": "http://www.bbc.co.uk/ontologies/applicationlogic-sport/ExternalWebsite"
            },
            {
              "@id": "http://www.irishfa.com/",
              "webDocumentCategory": "http://www.bbc.co.uk/ontologies/applicationlogic-sport/ExternalWebsite"
            },
            {
              "@id": "http://www.scottishfa.co.uk/",
              "webDocumentCategory": "http://www.bbc.co.uk/ontologies/applicationlogic-sport/ExternalWebsite"
            },
            {
              "@id": "http://www.thefa.com/",
              "webDocumentCategory": "http://www.bbc.co.uk/ontologies/applicationlogic-sport/ExternalWebsite"
            }
          ],
          "sameAs": "http://dbpedia.org/resource/Association_football"
        }
      ],
      "primaryContentOf": [
        {
          "@id": "http://www.bbc.co.uk/sport/football/50149823",
          "platform": "HighWeb",
          "webDocumentType": "HighWeb"
        }
      ],
      "thumbnail": [
        {
          "@id": "http://c.files.bbci.co.uk/141BB/production/_109336328_riverplate_getty.jpg",
          "@type": [
            "Thumbnail"
          ],
          "altText": "River Plate players celebrate reaching the final",
          "thumbnailType": "StandardThumbnail"
        }
      ]
    },
    {
      "@id": "http://www.bbc.co.uk/things/e165ae00-1f81-4497-8dab-4a3773fc440c#id",
      "@type": [
        "CreativeWork",
        "NewsItem"
      ],
      "dateCreated": "2019-10-22T16:32:11+00:00",
      "dateModified": "2019-10-22T16:32:11+00:00",
      "description": "Police arrest 16 Flamengo fans for \"threats to kill police\" before the Copa Libertadores semi-final second leg against Gremio in Brazil.",
      "shortTitle": "Flamengo fans arrested before semi",
      "title": "Copa Libertadores: Flamengo fans arrested before Gremio semi-final",
      "category": "http://www.bbc.co.uk/ontologies/applicationlogic-sport/News",
      "locator": [
        "urn:asset:0079a707-b3d8-ea41-b198-ddd3625a80ff",
        "urn:bbc:cps:asset:50137065"
      ],
      "primaryFormat": "TextualFormat",
      "about": [
        {
          "@id": "http://www.bbc.co.uk/things/0350ec6a-76af-4d2b-80f5-396998ce775b#id",
          "@type": [
            "Thing",
            "http://www.bbc.co.uk/ontologies/event/RecurringEvent",
            "sport:RecurringCompetition",
            "http://www.bbc.co.uk/ontologies/applicationlogic-sport/SportTopic",
            "sport:Competition"
          ],
          "label": "Brazilian Série A",
          "preferredLabel": "Brazilian Série A",
          "shortLabel": "Brazilian Série A",
          "slug": "brazilian-league",
          "primaryTopicOf": [
            {
              "@id": "http://www.bbc.co.uk/sport/football/brazilian-league",
              "webDocumentCategory": "http://www.bbc.co.uk/ontologies/applicationlogic-sport/Index"
            }
          ]
        },
        {
          "@id": "http://www.bbc.co.uk/things/4063f80f-cccc-44c8-9449-5ca44e4c8592#id",
          "@type": [
            "http://data.press.net/ontology/classification/Classification",
            "http://www.bbc.co.uk/ontologies/classification/RootClassification",
            "skos:Concept",
            "Thing",
            "Theme"
          ],
          "label": "Sport",
          "preferredLabel": "Sport",
          "shortLabel": "Sport",
          "slug": "sport",
          "primaryTopicOf": [
            "http://en.wikipedia.org/wiki/Sport",
            "http://www.bbc.co.uk/sport"
          ],
          "sameAs": "http://dbpedia.org/resource/Sport"
        },
        {
          "@id": "http://www.bbc.co.uk/things/6b71918f-e3a3-4dff-ad36-c3d737605d43#id",
          "@type": [
            "Thing",
            "sport:RecurringCompetition",
            "sport:Competition"
          ],
          "label": "Copa Libertadores",
          "preferredLabel": "Copa Libertadores",
          "shortLabel": "Copa Libertadores",
          "slug": "copa-libertadores",
          "sameAs": "http://dbpedia.org/resource/Copa_Libertadores",
          "primaryTopicOf": [
            {
              "@id": "http://www.bbc.co.uk/sport/football/copa-libertadores",
              "webDocumentCategory": "http://www.bbc.co.uk/ontologies/applicationlogic-sport/Index"
            }
          ]
        },
        {
          "@id": "http://www.bbc.co.uk/things/ba6e1118-f874-054e-b159-b797c16e9250#id",
          "@type": [
            "Thing",
            "sport:SportsDiscipline",
            "http://www.bbc.co.uk/ontologies/applicationlogic-sport/SportTopic",
            "Theme"
          ],
          "label": [
            "Football",
            "Football"
          ],
          "preferredLabel": "Football",
          "shortLabel": "Football",
          "slug": "football",
          "primaryTopicOf": [
            "http://en.wikipedia.org/wiki/Association_football",
            "http://www.bbc.co.uk/sport/football",
            "http://www.fifa.com/",
            {
              "@id": "http://www.faw.org.uk/",
              "webDocumentCategory": "http://www.bbc.co.uk/ontologies/applicationlogic-sport/ExternalWebsite"
            },
            {
              "@id": "http://www.irishfa.com/",
              "webDocumentCategory": "http://www.bbc.co.uk/ontologies/applicationlogic-sport/ExternalWebsite"
            },
            {
              "@id": "http://www.scottishfa.co.uk/",
              "webDocumentCategory": "http://www.bbc.co.uk/ontologies/applicationlogic-sport/ExternalWebsite"
            },
            {
              "@id": "http://www.thefa.com/",
              "webDocumentCategory": "http://www.bbc.co.uk/ontologies/applicationlogic-sport/ExternalWebsite"
            }
          ],
          "sameAs": "http://dbpedia.org/resource/Association_football"
        }
      ],
      "primaryContentOf": [
        {
          "@id": "http://www.bbc.co.uk/sport/football/50137065",
          "platform": "HighWeb",
          "webDocumentType": "HighWeb"
        }
      ],
      "thumbnail": [
        {
          "@id": "http://c.files.bbci.co.uk/12608/production/_109327257_gettyimages-1178679371.jpg",
          "@type": [
            "Thumbnail"
          ],
          "altText": "Flamengo and Gremio players",
          "thumbnailType": "StandardThumbnail"
        }
      ]
    },
    {
      "@id": "http://www.bbc.co.uk/things/b1d387ec-a626-4beb-95c5-c313496c7dfb#id",
      "@type": [
        "NewsItem",
        "CreativeWork"
      ],
      "dateCreated": "2019-09-30T19:01:02+00:00",
      "dateModified": "2019-09-30T19:01:02+00:00",
      "description": "Argentine rivals River Plate and Boca Juniors will meet in Wednesday\u0027s Copa Libertadores semi-final, nine months after their controversial 2018 final.",
      "shortTitle": "Rivals meet again in Copa Libertadores",
      "title": "Copa Libertadores: Boca Juniors \u0026 River Plate to do battle again",
      "category": "http://www.bbc.co.uk/ontologies/applicationlogic-sport/News",
      "locator": [
        "urn:asset:c0657375-c2ec-1148-a971-d36c458df6eb",
        "urn:bbc:cps:asset:49885830"
      ],
      "primaryFormat": "TextualFormat",
      "about": [
        {
          "@id": "http://www.bbc.co.uk/things/3a1503c2-ef90-4157-a7cc-3f3a62f28a76#id",
          "@type": [
            "http://www.bbc.co.uk/ontologies/applicationlogic-sport/SportTopic",
            "Thing",
            "skos:Concept",
            "http://data.press.net/ontology/classification/Classification"
          ],
          "label": "European Football",
          "preferredLabel": "European Football",
          "shortLabel": "European Football",
          "primaryTopicOf": "http://www.bbc.co.uk/sport/football/european"
        },
        {
          "@id": "http://www.bbc.co.uk/things/4063f80f-cccc-44c8-9449-5ca44e4c8592#id",
          "@type": [
            "http://data.press.net/ontology/classification/Classification",
            "http://www.bbc.co.uk/ontologies/classification/RootClassification",
            "skos:Concept",
            "Thing",
            "Theme"
          ],
          "label": "Sport",
          "preferredLabel": "Sport",
          "shortLabel": "Sport",
          "slug": "sport",
          "primaryTopicOf": [
            "http://en.wikipedia.org/wiki/Sport",
            "http://www.bbc.co.uk/sport"
          ],
          "sameAs": "http://dbpedia.org/resource/Sport"
        },
        {
          "@id": "http://www.bbc.co.uk/things/6b71918f-e3a3-4dff-ad36-c3d737605d43#id",
          "@type": [
            "Thing",
            "sport:RecurringCompetition",
            "sport:Competition"
          ],
          "label": "Copa Libertadores",
          "preferredLabel": "Copa Libertadores",
          "shortLabel": "Copa Libertadores",
          "slug": "copa-libertadores",
          "sameAs": "http://dbpedia.org/resource/Copa_Libertadores",
          "primaryTopicOf": [
            {
              "@id": "http://www.bbc.co.uk/sport/football/copa-libertadores",
              "webDocumentCategory": "http://www.bbc.co.uk/ontologies/applicationlogic-sport/Index"
            }
          ]
        },
        {
          "@id": "http://www.bbc.co.uk/things/ba6e1118-f874-054e-b159-b797c16e9250#id",
          "@type": [
            "Thing",
            "sport:SportsDiscipline",
            "http://www.bbc.co.uk/ontologies/applicationlogic-sport/SportTopic",
            "Theme"
          ],
          "label": [
            "Football",
            "Football"
          ],
          "preferredLabel": "Football",
          "shortLabel": "Football",
          "slug": "football",
          "primaryTopicOf": [
            "http://en.wikipedia.org/wiki/Association_football",
            "http://www.bbc.co.uk/sport/football",
            "http://www.fifa.com/",
            {
              "@id": "http://www.faw.org.uk/",
              "webDocumentCategory": "http://www.bbc.co.uk/ontologies/applicationlogic-sport/ExternalWebsite"
            },
            {
              "@id": "http://www.irishfa.com/",
              "webDocumentCategory": "http://www.bbc.co.uk/ontologies/applicationlogic-sport/ExternalWebsite"
            },
            {
              "@id": "http://www.scottishfa.co.uk/",
              "webDocumentCategory": "http://www.bbc.co.uk/ontologies/applicationlogic-sport/ExternalWebsite"
            },
            {
              "@id": "http://www.thefa.com/",
              "webDocumentCategory": "http://www.bbc.co.uk/ontologies/applicationlogic-sport/ExternalWebsite"
            }
          ],
          "sameAs": "http://dbpedia.org/resource/Association_football"
        }
      ],
      "primaryContentOf": [
        {
          "@id": "http://www.bbc.co.uk/sport/football/49885830",
          "platform": "HighWeb",
          "webDocumentType": "HighWeb"
        }
      ],
      "thumbnail": [
        {
          "@id": "http://c.files.bbci.co.uk/2B73/production/_109032111_gettyimages-1165542841.jpg",
          "@type": [
            "Thumbnail"
          ],
          "altText": "Carlos Tevez",
          "thumbnailType": "StandardThumbnail"
        }
      ]
    },
    {
      "@id": "http://www.bbc.co.uk/things/4b3f5296-24b7-4f4c-9c49-2fcefed5ee36#id",
      "@type": [
        "CreativeWork",
        "NewsItem"
      ],
      "dateCreated": "2019-04-12T08:18:40+00:00",
      "dateModified": "2019-04-12T08:18:40+00:00",
      "description": "A River Plate fan made sure he could access his side\u0027s goals against Boca Juniors in the Copa Libertadores final by having a QR code inked on his leg.",
      "shortTitle": "River Plate fan tattoos link to Copa Libertadores highlights on his leg",
      "title": "River Plate fan gets QR code tattoo linking to Copa Libertadores final highlights",
      "category": "http://www.bbc.co.uk/ontologies/applicationlogic-sport/News",
      "locator": [
        "urn:asset:5f1bdc3f-89d4-f340-aac3-7d9f9ff8dd81",
        "urn:bbc:cps:asset:47906720"
      ],
      "primaryFormat": "TextualFormat",
      "about": [
        {
          "@id": "http://www.bbc.co.uk/things/4063f80f-cccc-44c8-9449-5ca44e4c8592#id",
          "@type": [
            "http://data.press.net/ontology/classification/Classification",
            "http://www.bbc.co.uk/ontologies/classification/RootClassification",
            "skos:Concept",
            "Thing",
            "Theme"
          ],
          "label": "Sport",
          "preferredLabel": "Sport",
          "shortLabel": "Sport",
          "slug": "sport",
          "primaryTopicOf": [
            "http://en.wikipedia.org/wiki/Sport",
            "http://www.bbc.co.uk/sport"
          ],
          "sameAs": "http://dbpedia.org/resource/Sport"
        },
        {
          "@id": "http://www.bbc.co.uk/things/6b71918f-e3a3-4dff-ad36-c3d737605d43#id",
          "@type": [
            "Thing",
            "sport:RecurringCompetition",
            "sport:Competition"
          ],
          "label": "Copa Libertadores",
          "preferredLabel": "Copa Libertadores",
          "shortLabel": "Copa Libertadores",
          "slug": "copa-libertadores",
          "sameAs": "http://dbpedia.org/resource/Copa_Libertadores",
          "primaryTopicOf": [
            {
              "@id": "http://www.bbc.co.uk/sport/football/copa-libertadores",
              "webDocumentCategory": "http://www.bbc.co.uk/ontologies/applicationlogic-sport/Index"
            }
          ]
        },
        {
          "@id": "http://www.bbc.co.uk/things/ba6e1118-f874-054e-b159-b797c16e9250#id",
          "@type": [
            "Thing",
            "sport:SportsDiscipline",
            "http://www.bbc.co.uk/ontologies/applicationlogic-sport/SportTopic",
            "Theme"
          ],
          "label": [
            "Football",
            "Football"
          ],
          "preferredLabel": "Football",
          "shortLabel": "Football",
          "slug": "football",
          "primaryTopicOf": [
            "http://en.wikipedia.org/wiki/Association_football",
            "http://www.bbc.co.uk/sport/football",
            "http://www.fifa.com/",
            {
              "@id": "http://www.faw.org.uk/",
              "webDocumentCategory": "http://www.bbc.co.uk/ontologies/applicationlogic-sport/ExternalWebsite"
            },
            {
              "@id": "http://www.irishfa.com/",
              "webDocumentCategory": "http://www.bbc.co.uk/ontologies/applicationlogic-sport/ExternalWebsite"
            },
            {
              "@id": "http://www.scottishfa.co.uk/",
              "webDocumentCategory": "http://www.bbc.co.uk/ontologies/applicationlogic-sport/ExternalWebsite"
            },
            {
              "@id": "http://www.thefa.com/",
              "webDocumentCategory": "http://www.bbc.co.uk/ontologies/applicationlogic-sport/ExternalWebsite"
            }
          ],
          "sameAs": "http://dbpedia.org/resource/Association_football"
        }
      ],
      "primaryContentOf": [
        {
          "@id": "http://www.bbc.co.uk/sport/football/47906720",
          "platform": "HighWeb",
          "webDocumentType": "HighWeb"
        }
      ],
      "thumbnail": [
        {
          "@id": "http://c.files.bbci.co.uk/ADEA/production/_106422544_gettyimages-1070852594.jpg",
          "@type": [
            "Thumbnail"
          ],
          "altText": "River Plate fans celebrate their win against Boca Juniors",
          "thumbnailType": "StandardThumbnail"
        }
      ]
    },
    {
      "@id": "http://www.bbc.co.uk/things/77295306-25ae-4ae4-a687-883dc845e5af#id",
      "@type": [
        "CreativeWork",
        "NewsItem"
      ],
      "dateCreated": "2018-12-10T10:32:42+00:00",
      "dateModified": "2018-12-10T10:32:42+00:00",
      "description": "A \"fudged final\", a sign of things to come, or both? BBC Sport\u0027s Manu Djazmi assesses whether staging South America\u0027s biggest game in Europe was a success.",
      "shortTitle": "Did holding Superclasico in Madrid work?",
      "title": "Copa Libertadores final: Did staging River Plate v Boca Juniors in Madrid work?",
      "category": "http://www.bbc.co.uk/ontologies/applicationlogic-sport/News",
      "locator": [
        "urn:asset:4f5b9bb9-f17a-0f40-ba8c-5c7d0de1b701",
        "urn:bbc:cps:asset:46500504"
      ],
      "primaryFormat": "TextualFormat",
      "about": [
        {
          "@id": "http://www.bbc.co.uk/things/4063f80f-cccc-44c8-9449-5ca44e4c8592#id",
          "@type": [
            "http://data.press.net/ontology/classification/Classification",
            "http://www.bbc.co.uk/ontologies/classification/RootClassification",
            "skos:Concept",
            "Thing",
            "Theme"
          ],
          "label": "Sport",
          "preferredLabel": "Sport",
          "shortLabel": "Sport",
          "slug": "sport",
          "primaryTopicOf": [
            "http://en.wikipedia.org/wiki/Sport",
            "http://www.bbc.co.uk/sport"
          ],
          "sameAs": "http://dbpedia.org/resource/Sport"
        },
        {
          "@id": "http://www.bbc.co.uk/things/677f83fc-4aa8-422f-9a9e-685975882911#id",
          "@type": [
            "Thing",
            "Place",
            "geoname:GeoTagConcept"
          ],
          "label": "Buenos Aires",
          "preferredLabel": "Buenos Aires",
          "sameAs": "http://sws.geonames.org/3435910/"
        },
        {
          "@id": "http://www.bbc.co.uk/things/6b71918f-e3a3-4dff-ad36-c3d737605d43#id",
          "@type": [
            "Thing",
            "sport:RecurringCompetition",
            "sport:Competition"
          ],
          "label": "Copa Libertadores",
          "preferredLabel": "Copa Libertadores",
          "shortLabel": "Copa Libertadores",
          "slug": "copa-libertadores",
          "sameAs": "http://dbpedia.org/resource/Copa_Libertadores",
          "primaryTopicOf": [
            {
              "@id": "http://www.bbc.co.uk/sport/football/copa-libertadores",
              "webDocumentCategory": "http://www.bbc.co.uk/ontologies/applicationlogic-sport/Index"
            }
          ]
        },
        {
          "@id": "http://www.bbc.co.uk/things/ba6e1118-f874-054e-b159-b797c16e9250#id",
          "@type": [
            "Thing",
            "sport:SportsDiscipline",
            "http://www.bbc.co.uk/ontologies/applicationlogic-sport/SportTopic",
            "Theme"
          ],
          "label": [
            "Football",
            "Football"
          ],
          "preferredLabel": "Football",
          "shortLabel": "Football",
          "slug": "football",
          "primaryTopicOf": [
            "http://en.wikipedia.org/wiki/Association_football",
            "http://www.bbc.co.uk/sport/football",
            "http://www.fifa.com/",
            {
              "@id": "http://www.faw.org.uk/",
              "webDocumentCategory": "http://www.bbc.co.uk/ontologies/applicationlogic-sport/ExternalWebsite"
            },
            {
              "@id": "http://www.irishfa.com/",
              "webDocumentCategory": "http://www.bbc.co.uk/ontologies/applicationlogic-sport/ExternalWebsite"
            },
            {
              "@id": "http://www.scottishfa.co.uk/",
              "webDocumentCategory": "http://www.bbc.co.uk/ontologies/applicationlogic-sport/ExternalWebsite"
            },
            {
              "@id": "http://www.thefa.com/",
              "webDocumentCategory": "http://www.bbc.co.uk/ontologies/applicationlogic-sport/ExternalWebsite"
            }
          ],
          "sameAs": "http://dbpedia.org/resource/Association_football"
        },
        {
          "@id": "http://www.bbc.co.uk/things/bba327e1-7bf9-4e04-90af-8892bd3bc218#id",
          "@type": [
            "Thing",
            "Place",
            "geoname:GeoTagConcept"
          ],
          "label": "Madrid",
          "preferredLabel": "Madrid",
          "sameAs": "http://sws.geonames.org/3117735/"
        }
      ],
      "primaryContentOf": [
        {
          "@id": "http://www.bbc.co.uk/sport/football/46500504",
          "platform": "HighWeb",
          "webDocumentType": "HighWeb"
        }
      ],
      "thumbnail": [
        {
          "@id": "http://c.files.bbci.co.uk/12F16/production/_104709577_river_fans_getty.jpg",
          "@type": [
            "Thumbnail"
          ],
          "altText": "River Plate fans celebrate in the stands",
          "thumbnailType": "StandardThumbnail"
        }
      ]
    },
    {
      "@id": "http://www.bbc.co.uk/things/25779055-07e7-401a-8549-6047ea13566a#id",
      "@type": [
        "CreativeWork",
        "NewsItem"
      ],
      "dateCreated": "2018-12-09T23:46:34+00:00",
      "dateModified": "2018-12-09T23:46:34+00:00",
      "description": "Watch highlights as River Plate beat Boca Juniors 3-1 to claim their fourth Copa Libertadores trophy in front of 72,000 fans at Real Madrid\u0027s Bernabeu stadium.",
      "shortTitle": "River Plate beat Boca Juniors to win Copa Libertadores",
      "title": "River Plate beat Boca Juniors 3-1 to win the Copa Libertadores final",
      "category": "http://www.bbc.co.uk/ontologies/applicationlogic-sport/News",
      "locator": [
        "urn:asset:ffe5d6fa-017a-c344-ba32-b10f58f98c53",
        "urn:bbc:cps:asset:46502484"
      ],
      "primaryFormat": "VideoFormat",
      "about": [
        {
          "@id": "http://www.bbc.co.uk/things/4063f80f-cccc-44c8-9449-5ca44e4c8592#id",
          "@type": [
            "http://data.press.net/ontology/classification/Classification",
            "http://www.bbc.co.uk/ontologies/classification/RootClassification",
            "skos:Concept",
            "Thing",
            "Theme"
          ],
          "label": "Sport",
          "preferredLabel": "Sport",
          "shortLabel": "Sport",
          "slug": "sport",
          "primaryTopicOf": [
            "http://en.wikipedia.org/wiki/Sport",
            "http://www.bbc.co.uk/sport"
          ],
          "sameAs": "http://dbpedia.org/resource/Sport"
        },
        {
          "@id": "http://www.bbc.co.uk/things/677f83fc-4aa8-422f-9a9e-685975882911#id",
          "@type": [
            "Thing",
            "Place",
            "geoname:GeoTagConcept"
          ],
          "label": "Buenos Aires",
          "preferredLabel": "Buenos Aires",
          "sameAs": "http://sws.geonames.org/3435910/"
        },
        {
          "@id": "http://www.bbc.co.uk/things/6b71918f-e3a3-4dff-ad36-c3d737605d43#id",
          "@type": [
            "Thing",
            "sport:RecurringCompetition",
            "sport:Competition"
          ],
          "label": "Copa Libertadores",
          "preferredLabel": "Copa Libertadores",
          "shortLabel": "Copa Libertadores",
          "slug": "copa-libertadores",
          "sameAs": "http://dbpedia.org/resource/Copa_Libertadores",
          "primaryTopicOf": [
            {
              "@id": "http://www.bbc.co.uk/sport/football/copa-libertadores",
              "webDocumentCategory": "http://www.bbc.co.uk/ontologies/applicationlogic-sport/Index"
            }
          ]
        },
        {
          "@id": "http://www.bbc.co.uk/things/ba6e1118-f874-054e-b159-b797c16e9250#id",
          "@type": [
            "Thing",
            "sport:SportsDiscipline",
            "http://www.bbc.co.uk/ontologies/applicationlogic-sport/SportTopic",
            "Theme"
          ],
          "label": [
            "Football",
            "Football"
          ],
          "preferredLabel": "Football",
          "shortLabel": "Football",
          "slug": "football",
          "primaryTopicOf": [
            "http://en.wikipedia.org/wiki/Association_football",
            "http://www.bbc.co.uk/sport/football",
            "http://www.fifa.com/",
            {
              "@id": "http://www.faw.org.uk/",
              "webDocumentCategory": "http://www.bbc.co.uk/ontologies/applicationlogic-sport/ExternalWebsite"
            },
            {
              "@id": "http://www.irishfa.com/",
              "webDocumentCategory": "http://www.bbc.co.uk/ontologies/applicationlogic-sport/ExternalWebsite"
            },
            {
              "@id": "http://www.scottishfa.co.uk/",
              "webDocumentCategory": "http://www.bbc.co.uk/ontologies/applicationlogic-sport/ExternalWebsite"
            },
            {
              "@id": "http://www.thefa.com/",
              "webDocumentCategory": "http://www.bbc.co.uk/ontologies/applicationlogic-sport/ExternalWebsite"
            }
          ],
          "sameAs": "http://dbpedia.org/resource/Association_football"
        },
        {
          "@id": "http://www.bbc.co.uk/things/bba327e1-7bf9-4e04-90af-8892bd3bc218#id",
          "@type": [
            "Thing",
            "Place",
            "geoname:GeoTagConcept"
          ],
          "label": "Madrid",
          "preferredLabel": "Madrid",
          "sameAs": "http://sws.geonames.org/3117735/"
        }
      ],
      "primaryContentOf": [
        {
          "@id": "http://www.bbc.co.uk/sport/av/football/46502484",
          "platform": "HighWeb",
          "webDocumentType": "HighWeb"
        }
      ],
      "thumbnail": [
        {
          "@id": "http://c.files.bbci.co.uk/332D/production/_104710131_p06v3s6q.jpg",
          "@type": [
            "Thumbnail"
          ],
          "altText": "Boca Juniors",
          "thumbnailType": "StandardThumbnail"
        }
      ]
    },
    {
      "@id": "http://www.bbc.co.uk/things/ff2ad459-97e4-4ccd-8d86-5ce9662dc838#id",
      "@type": [
        "CreativeWork",
        "LiveCoverage"
      ],
      "dateCreated": "2018-12-08T16:58:27+00:00",
      "dateModified": "2018-12-08T16:58:27+00:00",
      "description": "River Plate face Boca Juniors in the second leg of the Copa Libertadores final at the Santiago Bernabeu in Madrid - follow live text commentary.",
      "shortTitle": "Copa Libertadores: River Plate out-last Boca in marathon final",
      "title": "River Plate v Boca Juniors live in the Copa Libertadores final second leg",
      "category": "http://www.bbc.co.uk/ontologies/applicationlogic-sport/News",
      "locator": [
        "urn:asset:ff42ae24-be5c-7148-aee9-701d82a47e91",
        "urn:bbc:cps:asset:46445525"
      ],
      "primaryFormat": "TextualFormat",
      "about": [
        {
          "@id": "http://www.bbc.co.uk/things/6b71918f-e3a3-4dff-ad36-c3d737605d43#id",
          "@type": [
            "Thing",
            "sport:RecurringCompetition",
            "sport:Competition"
          ],
          "label": "Copa Libertadores",
          "preferredLabel": "Copa Libertadores",
          "shortLabel": "Copa Libertadores",
          "slug": "copa-libertadores",
          "sameAs": "http://dbpedia.org/resource/Copa_Libertadores",
          "primaryTopicOf": [
            {
              "@id": "http://www.bbc.co.uk/sport/football/copa-libertadores",
              "webDocumentCategory": "http://www.bbc.co.uk/ontologies/applicationlogic-sport/Index"
            }
          ]
        }
      ],
      "primaryContentOf": [
        {
          "@id": "http://www.bbc.co.uk/sport/live/football/46445525",
          "platform": "HighWeb",
          "webDocumentType": "HighWeb"
        }
      ],
      "thumbnail": [
        {
          "@id": "http://c.files.bbci.co.uk/3490/production/_104665431_enzoperezandpabloperez_getty.jpg",
          "@type": [
            "Thumbnail"
          ],
          "altText": "Enzo Perez and Pablo Perez battle for the ball",
          "thumbnailType": "StandardThumbnail"
        }
      ]
    },
    {
      "@id": "http://www.bbc.co.uk/things/5e115c45-8a96-4928-8c3c-61ff4178e7da#id",
      "@type": [
        "NewsItem",
        "CreativeWork"
      ],
      "dateCreated": "2018-12-08T15:03:47+00:00",
      "dateModified": "2018-12-08T15:03:47+00:00",
      "description": "Boca Juniors have a late attempt to postpone Sunday\u0027s Copa Libertadores final second leg rejected by the Court of Arbitration for Sport.",
      "shortTitle": "Boca bid to postpone Copa final rejected",
      "title": "Copa Libertadores final: Boca Juniors\u0027 bid to postpone match rejected by Cas",
      "category": "http://www.bbc.co.uk/ontologies/applicationlogic-sport/News",
      "locator": [
        "urn:asset:b620be27-d5fa-af4e-b2aa-b368cc0f4fc3",
        "urn:bbc:cps:asset:46493291"
      ],
      "primaryFormat": "TextualFormat",
      "about": [
        {
          "@id": "http://www.bbc.co.uk/things/4063f80f-cccc-44c8-9449-5ca44e4c8592#id",
          "@type": [
            "http://data.press.net/ontology/classification/Classification",
            "http://www.bbc.co.uk/ontologies/classification/RootClassification",
            "skos:Concept",
            "Thing",
            "Theme"
          ],
          "label": "Sport",
          "preferredLabel": "Sport",
          "shortLabel": "Sport",
          "slug": "sport",
          "primaryTopicOf": [
            "http://en.wikipedia.org/wiki/Sport",
            "http://www.bbc.co.uk/sport"
          ],
          "sameAs": "http://dbpedia.org/resource/Sport"
        },
        {
          "@id": "http://www.bbc.co.uk/things/467fd84f-5bf7-419e-9bd3-a0963c9cebbf#id",
          "@type": [
            "sport:Competition",
            "sport:RecurringCompetition",
            "http://www.bbc.co.uk/ontologies/applicationlogic-sport/SportTopic",
            "Thing",
            "http://www.bbc.co.uk/ontologies/event/RecurringEvent"
          ],
          "label": "Argentine Primera Division",
          "preferredLabel": "Argentine Primera Division",
          "shortLabel": "Argentine Primera",
          "slug": "argentine-primera-division",
          "primaryTopicOf": [
            {
              "@id": "http://www.bbc.co.uk/sport/football/argentine-primera-division",
              "webDocumentCategory": "http://www.bbc.co.uk/ontologies/applicationlogic-sport/Index"
            }
          ]
        },
        {
          "@id": "http://www.bbc.co.uk/things/6b71918f-e3a3-4dff-ad36-c3d737605d43#id",
          "@type": [
            "Thing",
            "sport:RecurringCompetition",
            "sport:Competition"
          ],
          "label": "Copa Libertadores",
          "preferredLabel": "Copa Libertadores",
          "shortLabel": "Copa Libertadores",
          "slug": "copa-libertadores",
          "sameAs": "http://dbpedia.org/resource/Copa_Libertadores",
          "primaryTopicOf": [
            {
              "@id": "http://www.bbc.co.uk/sport/football/copa-libertadores",
              "webDocumentCategory": "http://www.bbc.co.uk/ontologies/applicationlogic-sport/Index"
            }
          ]
        },
        {
          "@id": "http://www.bbc.co.uk/things/ba6e1118-f874-054e-b159-b797c16e9250#id",
          "@type": [
            "Thing",
            "sport:SportsDiscipline",
            "http://www.bbc.co.uk/ontologies/applicationlogic-sport/SportTopic",
            "Theme"
          ],
          "label": [
            "Football",
            "Football"
          ],
          "preferredLabel": "Football",
          "shortLabel": "Football",
          "slug": "football",
          "primaryTopicOf": [
            "http://en.wikipedia.org/wiki/Association_football",
            "http://www.bbc.co.uk/sport/football",
            "http://www.fifa.com/",
            {
              "@id": "http://www.faw.org.uk/",
              "webDocumentCategory": "http://www.bbc.co.uk/ontologies/applicationlogic-sport/ExternalWebsite"
            },
            {
              "@id": "http://www.irishfa.com/",
              "webDocumentCategory": "http://www.bbc.co.uk/ontologies/applicationlogic-sport/ExternalWebsite"
            },
            {
              "@id": "http://www.scottishfa.co.uk/",
              "webDocumentCategory": "http://www.bbc.co.uk/ontologies/applicationlogic-sport/ExternalWebsite"
            },
            {
              "@id": "http://www.thefa.com/",
              "webDocumentCategory": "http://www.bbc.co.uk/ontologies/applicationlogic-sport/ExternalWebsite"
            }
          ],
          "sameAs": "http://dbpedia.org/resource/Association_football"
        }
      ],
      "primaryContentOf": [
        {
          "@id": "http://www.bbc.co.uk/sport/football/46493291",
          "platform": "HighWeb",
          "webDocumentType": "HighWeb"
        }
      ],
      "thumbnail": [
        {
          "@id": "http://c.files.bbci.co.uk/D9F8/production/_104700855_copalibertadoresmagnets.jpg",
          "@type": [
            "Thumbnail"
          ],
          "altText": "Copa Libertadores plaques",
          "thumbnailType": "StandardThumbnail"
        }
      ]
    },
    {
      "@id": "http://www.bbc.co.uk/things/6cfb18cb-7eb5-4445-bf24-febfb502516c#id",
      "@type": [
        "NewsItem",
        "CreativeWork"
      ],
      "dateCreated": "2018-12-07T07:47:46+00:00",
      "dateModified": "2018-12-07T07:47:46+00:00",
      "description": "Boca Juniors forward Carlos Tevez says the Copa Libertadores attack on his team\u0027s bus by River Plate fans \"took away players\u0027 dreams\".",
      "shortTitle": "Madrid final \u0027embarrassing\u0027 - Tevez",
      "title": "Copa Libertadores final: Boca Juniors v River Plate in Madrid \u0027embarrassing\u0027",
      "category": "http://www.bbc.co.uk/ontologies/applicationlogic-sport/News",
      "locator": [
        "urn:asset:97bb036c-c2f4-7343-a5e2-4f3c3d4dd438",
        "urn:bbc:cps:asset:46479525"
      ],
      "primaryFormat": "TextualFormat",
      "about": [
        {
          "@id": "http://www.bbc.co.uk/things/4063f80f-cccc-44c8-9449-5ca44e4c8592#id",
          "@type": [
            "http://data.press.net/ontology/classification/Classification",
            "http://www.bbc.co.uk/ontologies/classification/RootClassification",
            "skos:Concept",
            "Thing",
            "Theme"
          ],
          "label": "Sport",
          "preferredLabel": "Sport",
          "shortLabel": "Sport",
          "slug": "sport",
          "primaryTopicOf": [
            "http://en.wikipedia.org/wiki/Sport",
            "http://www.bbc.co.uk/sport"
          ],
          "sameAs": "http://dbpedia.org/resource/Sport"
        },
        {
          "@id": "http://www.bbc.co.uk/things/467fd84f-5bf7-419e-9bd3-a0963c9cebbf#id",
          "@type": [
            "sport:Competition",
            "sport:RecurringCompetition",
            "http://www.bbc.co.uk/ontologies/applicationlogic-sport/SportTopic",
            "Thing",
            "http://www.bbc.co.uk/ontologies/event/RecurringEvent"
          ],
          "label": "Argentine Primera Division",
          "preferredLabel": "Argentine Primera Division",
          "shortLabel": "Argentine Primera",
          "slug": "argentine-primera-division",
          "primaryTopicOf": [
            {
              "@id": "http://www.bbc.co.uk/sport/football/argentine-primera-division",
              "webDocumentCategory": "http://www.bbc.co.uk/ontologies/applicationlogic-sport/Index"
            }
          ]
        },
        {
          "@id": "http://www.bbc.co.uk/things/6b71918f-e3a3-4dff-ad36-c3d737605d43#id",
          "@type": [
            "Thing",
            "sport:RecurringCompetition",
            "sport:Competition"
          ],
          "label": "Copa Libertadores",
          "preferredLabel": "Copa Libertadores",
          "shortLabel": "Copa Libertadores",
          "slug": "copa-libertadores",
          "sameAs": "http://dbpedia.org/resource/Copa_Libertadores",
          "primaryTopicOf": [
            {
              "@id": "http://www.bbc.co.uk/sport/football/copa-libertadores",
              "webDocumentCategory": "http://www.bbc.co.uk/ontologies/applicationlogic-sport/Index"
            }
          ]
        },
        {
          "@id": "http://www.bbc.co.uk/things/ba6e1118-f874-054e-b159-b797c16e9250#id",
          "@type": [
            "Thing",
            "sport:SportsDiscipline",
            "http://www.bbc.co.uk/ontologies/applicationlogic-sport/SportTopic",
            "Theme"
          ],
          "label": [
            "Football",
            "Football"
          ],
          "preferredLabel": "Football",
          "shortLabel": "Football",
          "slug": "football",
          "primaryTopicOf": [
            "http://en.wikipedia.org/wiki/Association_football",
            "http://www.bbc.co.uk/sport/football",
            "http://www.fifa.com/",
            {
              "@id": "http://www.faw.org.uk/",
              "webDocumentCategory": "http://www.bbc.co.uk/ontologies/applicationlogic-sport/ExternalWebsite"
            },
            {
              "@id": "http://www.irishfa.com/",
              "webDocumentCategory": "http://www.bbc.co.uk/ontologies/applicationlogic-sport/ExternalWebsite"
            },
            {
              "@id": "http://www.scottishfa.co.uk/",
              "webDocumentCategory": "http://www.bbc.co.uk/ontologies/applicationlogic-sport/ExternalWebsite"
            },
            {
              "@id": "http://www.thefa.com/",
              "webDocumentCategory": "http://www.bbc.co.uk/ontologies/applicationlogic-sport/ExternalWebsite"
            }
          ],
          "sameAs": "http://dbpedia.org/resource/Association_football"
        }
      ],
      "primaryContentOf": [
        {
          "@id": "http://www.bbc.co.uk/sport/football/46479525",
          "platform": "HighWeb",
          "webDocumentType": "HighWeb"
        }
      ],
      "thumbnail": [
        {
          "@id": "http://c.files.bbci.co.uk/40FE/production/_104683661_tevez_reuters.jpg",
          "@type": [
            "Thumbnail"
          ],
          "altText": "Carlos Tevez",
          "thumbnailType": "StandardThumbnail"
        }
      ]
    },
    {
      "@id": "http://www.bbc.co.uk/things/be9669e6-82c2-448a-9bb7-0b406d6a7740#id",
      "@type": [
        "NewsItem",
        "CreativeWork"
      ],
      "dateCreated": "2018-12-03T20:15:15+00:00",
      "dateModified": "2018-12-03T20:15:15+00:00",
      "description": "River Plate coach Marcelo Gallardo says moving the Copa Libertadores final from Argentina to Madrid is \"robbing the fans\" and a \"total disgrace\".",
      "shortTitle": "Madrid switch is \u0027robbing the fans\u0027",
      "title": "Copa Libertadores final switch to Madrid is \u0027robbing fans\u0027 - Marcelo Gallardo",
      "category": "http://www.bbc.co.uk/ontologies/applicationlogic-sport/News",
      "locator": [
        "urn:asset:047a613e-66fb-0e4f-bba3-8145d0140575",
        "urn:bbc:cps:asset:46433666"
      ],
      "primaryFormat": "TextualFormat",
      "about": [
        {
          "@id": "http://www.bbc.co.uk/things/4063f80f-cccc-44c8-9449-5ca44e4c8592#id",
          "@type": [
            "http://data.press.net/ontology/classification/Classification",
            "http://www.bbc.co.uk/ontologies/classification/RootClassification",
            "skos:Concept",
            "Thing",
            "Theme"
          ],
          "label": "Sport",
          "preferredLabel": "Sport",
          "shortLabel": "Sport",
          "slug": "sport",
          "primaryTopicOf": [
            "http://en.wikipedia.org/wiki/Sport",
            "http://www.bbc.co.uk/sport"
          ],
          "sameAs": "http://dbpedia.org/resource/Sport"
        },
        {
          "@id": "http://www.bbc.co.uk/things/6b71918f-e3a3-4dff-ad36-c3d737605d43#id",
          "@type": [
            "Thing",
            "sport:RecurringCompetition",
            "sport:Competition"
          ],
          "label": "Copa Libertadores",
          "preferredLabel": "Copa Libertadores",
          "shortLabel": "Copa Libertadores",
          "slug": "copa-libertadores",
          "sameAs": "http://dbpedia.org/resource/Copa_Libertadores",
          "primaryTopicOf": [
            {
              "@id": "http://www.bbc.co.uk/sport/football/copa-libertadores",
              "webDocumentCategory": "http://www.bbc.co.uk/ontologies/applicationlogic-sport/Index"
            }
          ]
        },
        {
          "@id": "http://www.bbc.co.uk/things/ba6e1118-f874-054e-b159-b797c16e9250#id",
          "@type": [
            "Thing",
            "sport:SportsDiscipline",
            "http://www.bbc.co.uk/ontologies/applicationlogic-sport/SportTopic",
            "Theme"
          ],
          "label": [
            "Football",
            "Football"
          ],
          "preferredLabel": "Football",
          "shortLabel": "Football",
          "slug": "football",
          "primaryTopicOf": [
            "http://en.wikipedia.org/wiki/Association_football",
            "http://www.bbc.co.uk/sport/football",
            "http://www.fifa.com/",
            {
              "@id": "http://www.faw.org.uk/",
              "webDocumentCategory": "http://www.bbc.co.uk/ontologies/applicationlogic-sport/ExternalWebsite"
            },
            {
              "@id": "http://www.irishfa.com/",
              "webDocumentCategory": "http://www.bbc.co.uk/ontologies/applicationlogic-sport/ExternalWebsite"
            },
            {
              "@id": "http://www.scottishfa.co.uk/",
              "webDocumentCategory": "http://www.bbc.co.uk/ontologies/applicationlogic-sport/ExternalWebsite"
            },
            {
              "@id": "http://www.thefa.com/",
              "webDocumentCategory": "http://www.bbc.co.uk/ontologies/applicationlogic-sport/ExternalWebsite"
            }
          ],
          "sameAs": "http://dbpedia.org/resource/Association_football"
        }
      ],
      "primaryContentOf": [
        {
          "@id": "http://www.bbc.co.uk/sport/football/46433666",
          "platform": "HighWeb",
          "webDocumentType": "HighWeb"
        }
      ],
      "thumbnail": [
        {
          "@id": "http://c.files.bbci.co.uk/492A/production/_104603781_bernabeu_getty.jpg",
          "@type": [
            "Thumbnail"
          ],
          "altText": "Real Madrid\u0027s Bernabeu Stadium",
          "thumbnailType": "StandardThumbnail"
        }
      ]
    },
    {
      "@id": "http://www.bbc.co.uk/things/215882bd-f14c-419a-bf7f-c63f47299278#id",
      "@type": [
        "NewsItem",
        "CreativeWork"
      ],
      "dateCreated": "2018-12-01T18:28:38+00:00",
      "dateModified": "2018-12-01T18:28:38+00:00",
      "description": "Argentine side River Plate object to playing the postponed second leg of their Copa Libertadores final against Boca Juniors in Madrid.",
      "shortTitle": "River Plate oppose Madrid final switch",
      "title": "River Plate oppose playing Copa Libertadores final in Madrid",
      "category": "http://www.bbc.co.uk/ontologies/applicationlogic-sport/News",
      "locator": [
        "urn:asset:0552beca-ab3a-8e4a-9acb-0664671f2330",
        "urn:bbc:cps:asset:46414287"
      ],
      "primaryFormat": "TextualFormat",
      "about": [
        {
          "@id": "http://www.bbc.co.uk/things/4063f80f-cccc-44c8-9449-5ca44e4c8592#id",
          "@type": [
            "http://data.press.net/ontology/classification/Classification",
            "http://www.bbc.co.uk/ontologies/classification/RootClassification",
            "skos:Concept",
            "Thing",
            "Theme"
          ],
          "label": "Sport",
          "preferredLabel": "Sport",
          "shortLabel": "Sport",
          "slug": "sport",
          "primaryTopicOf": [
            "http://en.wikipedia.org/wiki/Sport",
            "http://www.bbc.co.uk/sport"
          ],
          "sameAs": "http://dbpedia.org/resource/Sport"
        },
        {
          "@id": "http://www.bbc.co.uk/things/6b71918f-e3a3-4dff-ad36-c3d737605d43#id",
          "@type": [
            "Thing",
            "sport:RecurringCompetition",
            "sport:Competition"
          ],
          "label": "Copa Libertadores",
          "preferredLabel": "Copa Libertadores",
          "shortLabel": "Copa Libertadores",
          "slug": "copa-libertadores",
          "sameAs": "http://dbpedia.org/resource/Copa_Libertadores",
          "primaryTopicOf": [
            {
              "@id": "http://www.bbc.co.uk/sport/football/copa-libertadores",
              "webDocumentCategory": "http://www.bbc.co.uk/ontologies/applicationlogic-sport/Index"
            }
          ]
        },
        {
          "@id": "http://www.bbc.co.uk/things/ba6e1118-f874-054e-b159-b797c16e9250#id",
          "@type": [
            "Thing",
            "sport:SportsDiscipline",
            "http://www.bbc.co.uk/ontologies/applicationlogic-sport/SportTopic",
            "Theme"
          ],
          "label": [
            "Football",
            "Football"
          ],
          "preferredLabel": "Football",
          "shortLabel": "Football",
          "slug": "football",
          "primaryTopicOf": [
            "http://en.wikipedia.org/wiki/Association_football",
            "http://www.bbc.co.uk/sport/football",
            "http://www.fifa.com/",
            {
              "@id": "http://www.faw.org.uk/",
              "webDocumentCategory": "http://www.bbc.co.uk/ontologies/applicationlogic-sport/ExternalWebsite"
            },
            {
              "@id": "http://www.irishfa.com/",
              "webDocumentCategory": "http://www.bbc.co.uk/ontologies/applicationlogic-sport/ExternalWebsite"
            },
            {
              "@id": "http://www.scottishfa.co.uk/",
              "webDocumentCategory": "http://www.bbc.co.uk/ontologies/applicationlogic-sport/ExternalWebsite"
            },
            {
              "@id": "http://www.thefa.com/",
              "webDocumentCategory": "http://www.bbc.co.uk/ontologies/applicationlogic-sport/ExternalWebsite"
            }
          ],
          "sameAs": "http://dbpedia.org/resource/Association_football"
        }
      ],
      "primaryContentOf": [
        {
          "@id": "http://www.bbc.co.uk/sport/football/46414287",
          "platform": "HighWeb",
          "webDocumentType": "HighWeb"
        }
      ],
      "thumbnail": [
        {
          "@id": "http://c.files.bbci.co.uk/A91E/production/_104549234_bernabeu_getty.jpg",
          "@type": [
            "Thumbnail"
          ],
          "altText": "Bernabeu stadium",
          "thumbnailType": "StandardThumbnail"
        }
      ]
    },
    {
      "@id": "http://www.bbc.co.uk/things/0edfaaec-e551-4199-a54c-54e88e9fe7d0#id",
      "@type": [
        "CreativeWork",
        "NewsItem"
      ],
      "dateCreated": "2018-11-29T23:19:37+00:00",
      "dateModified": "2018-11-29T23:19:37+00:00",
      "description": "The second leg of the Copa Libertadores final between Boca Juniors and River Plate is moved 6,000 miles away to Madrid\u0027s Bernabeu.",
      "shortTitle": "Copa Libertadores moved to Madrid",
      "title": "Copa Libertadores: River Plate v Boca Juniors moved to Bernabeu in Madrid",
      "category": "http://www.bbc.co.uk/ontologies/applicationlogic-sport/News",
      "locator": [
        "urn:asset:ae2a304b-16ce-7840-a9ed-c421f1ad924e",
        "urn:bbc:cps:asset:46392340"
      ],
      "primaryFormat": "TextualFormat",
      "about": [
        {
          "@id": "http://www.bbc.co.uk/things/467fd84f-5bf7-419e-9bd3-a0963c9cebbf#id",
          "@type": [
            "sport:Competition",
            "sport:RecurringCompetition",
            "http://www.bbc.co.uk/ontologies/applicationlogic-sport/SportTopic",
            "Thing",
            "http://www.bbc.co.uk/ontologies/event/RecurringEvent"
          ],
          "label": "Argentine Primera Division",
          "preferredLabel": "Argentine Primera Division",
          "shortLabel": "Argentine Primera",
          "slug": "argentine-primera-division",
          "primaryTopicOf": [
            {
              "@id": "http://www.bbc.co.uk/sport/football/argentine-primera-division",
              "webDocumentCategory": "http://www.bbc.co.uk/ontologies/applicationlogic-sport/Index"
            }
          ]
        },
        {
          "@id": "http://www.bbc.co.uk/things/677f83fc-4aa8-422f-9a9e-685975882911#id",
          "@type": [
            "Thing",
            "Place",
            "geoname:GeoTagConcept"
          ],
          "label": "Buenos Aires",
          "preferredLabel": "Buenos Aires",
          "sameAs": "http://sws.geonames.org/3435910/"
        },
        {
          "@id": "http://www.bbc.co.uk/things/6b71918f-e3a3-4dff-ad36-c3d737605d43#id",
          "@type": [
            "Thing",
            "sport:RecurringCompetition",
            "sport:Competition"
          ],
          "label": "Copa Libertadores",
          "preferredLabel": "Copa Libertadores",
          "shortLabel": "Copa Libertadores",
          "slug": "copa-libertadores",
          "sameAs": "http://dbpedia.org/resource/Copa_Libertadores",
          "primaryTopicOf": [
            {
              "@id": "http://www.bbc.co.uk/sport/football/copa-libertadores",
              "webDocumentCategory": "http://www.bbc.co.uk/ontologies/applicationlogic-sport/Index"
            }
          ]
        },
        {
          "@id": "http://www.bbc.co.uk/things/ba6e1118-f874-054e-b159-b797c16e9250#id",
          "@type": [
            "Thing",
            "sport:SportsDiscipline",
            "http://www.bbc.co.uk/ontologies/applicationlogic-sport/SportTopic",
            "Theme"
          ],
          "label": [
            "Football",
            "Football"
          ],
          "preferredLabel": "Football",
          "shortLabel": "Football",
          "slug": "football",
          "primaryTopicOf": [
            "http://en.wikipedia.org/wiki/Association_football",
            "http://www.bbc.co.uk/sport/football",
            "http://www.fifa.com/",
            {
              "@id": "http://www.faw.org.uk/",
              "webDocumentCategory": "http://www.bbc.co.uk/ontologies/applicationlogic-sport/ExternalWebsite"
            },
            {
              "@id": "http://www.irishfa.com/",
              "webDocumentCategory": "http://www.bbc.co.uk/ontologies/applicationlogic-sport/ExternalWebsite"
            },
            {
              "@id": "http://www.scottishfa.co.uk/",
              "webDocumentCategory": "http://www.bbc.co.uk/ontologies/applicationlogic-sport/ExternalWebsite"
            },
            {
              "@id": "http://www.thefa.com/",
              "webDocumentCategory": "http://www.bbc.co.uk/ontologies/applicationlogic-sport/ExternalWebsite"
            }
          ],
          "sameAs": "http://dbpedia.org/resource/Association_football"
        }
      ],
      "primaryContentOf": [
        {
          "@id": "http://www.bbc.co.uk/sport/football/46392340",
          "platform": "HighWeb",
          "webDocumentType": "HighWeb"
        }
      ],
      "thumbnail": [
        {
          "@id": "http://c.files.bbci.co.uk/A91E/production/_104549234_bernabeu_getty.jpg",
          "@type": [
            "Thumbnail"
          ],
          "altText": "Bernabeu stadium",
          "thumbnailType": "StandardThumbnail"
        }
      ]
    },
    {
      "@id": "http://www.bbc.co.uk/things/6e4804c9-3c6e-4433-9df2-98e761c0b3b1#id",
      "@type": [
        "NewsItem",
        "CreativeWork"
      ],
      "dateCreated": "2018-11-27T16:09:33+00:00",
      "dateModified": "2018-11-27T16:09:33+00:00",
      "description": "The postponed Copa Libertadores final second leg between River Plate and Boca Juniors will take place on 8 or 9 December but will not be held in Argentina.",
      "shortTitle": "Copa Libertadores final date announced",
      "title": "River Plate v Boca Juniors: Postponed Copa Libertadores final second leg will not be held in Argentina",
      "category": "http://www.bbc.co.uk/ontologies/applicationlogic-sport/News",
      "locator": [
        "urn:asset:d65d7027-5bdf-0e40-8232-072090976b8c",
        "urn:bbc:cps:asset:46363739"
      ],
      "primaryFormat": "TextualFormat",
      "about": [
        {
          "@id": "http://www.bbc.co.uk/things/4063f80f-cccc-44c8-9449-5ca44e4c8592#id",
          "@type": [
            "http://data.press.net/ontology/classification/Classification",
            "http://www.bbc.co.uk/ontologies/classification/RootClassification",
            "skos:Concept",
            "Thing",
            "Theme"
          ],
          "label": "Sport",
          "preferredLabel": "Sport",
          "shortLabel": "Sport",
          "slug": "sport",
          "primaryTopicOf": [
            "http://en.wikipedia.org/wiki/Sport",
            "http://www.bbc.co.uk/sport"
          ],
          "sameAs": "http://dbpedia.org/resource/Sport"
        },
        {
          "@id": "http://www.bbc.co.uk/things/6b71918f-e3a3-4dff-ad36-c3d737605d43#id",
          "@type": [
            "Thing",
            "sport:RecurringCompetition",
            "sport:Competition"
          ],
          "label": "Copa Libertadores",
          "preferredLabel": "Copa Libertadores",
          "shortLabel": "Copa Libertadores",
          "slug": "copa-libertadores",
          "sameAs": "http://dbpedia.org/resource/Copa_Libertadores",
          "primaryTopicOf": [
            {
              "@id": "http://www.bbc.co.uk/sport/football/copa-libertadores",
              "webDocumentCategory": "http://www.bbc.co.uk/ontologies/applicationlogic-sport/Index"
            }
          ]
        },
        {
          "@id": "http://www.bbc.co.uk/things/ba6e1118-f874-054e-b159-b797c16e9250#id",
          "@type": [
            "Thing",
            "sport:SportsDiscipline",
            "http://www.bbc.co.uk/ontologies/applicationlogic-sport/SportTopic",
            "Theme"
          ],
          "label": [
            "Football",
            "Football"
          ],
          "preferredLabel": "Football",
          "shortLabel": "Football",
          "slug": "football",
          "primaryTopicOf": [
            "http://en.wikipedia.org/wiki/Association_football",
            "http://www.bbc.co.uk/sport/football",
            "http://www.fifa.com/",
            {
              "@id": "http://www.faw.org.uk/",
              "webDocumentCategory": "http://www.bbc.co.uk/ontologies/applicationlogic-sport/ExternalWebsite"
            },
            {
              "@id": "http://www.irishfa.com/",
              "webDocumentCategory": "http://www.bbc.co.uk/ontologies/applicationlogic-sport/ExternalWebsite"
            },
            {
              "@id": "http://www.scottishfa.co.uk/",
              "webDocumentCategory": "http://www.bbc.co.uk/ontologies/applicationlogic-sport/ExternalWebsite"
            },
            {
              "@id": "http://www.thefa.com/",
              "webDocumentCategory": "http://www.bbc.co.uk/ontologies/applicationlogic-sport/ExternalWebsite"
            }
          ],
          "sameAs": "http://dbpedia.org/resource/Association_football"
        }
      ],
      "primaryContentOf": [
        {
          "@id": "http://www.bbc.co.uk/sport/football/46363739",
          "platform": "HighWeb",
          "webDocumentType": "HighWeb"
        }
      ],
      "thumbnail": [
        {
          "@id": "http://c.files.bbci.co.uk/08C1/production/_104514220_riotpolice_getty.jpg",
          "@type": [
            "Thumbnail"
          ],
          "altText": "Riot police",
          "thumbnailType": "StandardThumbnail"
        }
      ]
    },
    {
      "@id": "http://www.bbc.co.uk/things/61167be0-9362-42a4-9c28-9e2483581545#id",
      "@type": [
        "NewsItem",
        "CreativeWork"
      ],
      "dateCreated": "2018-11-26T16:33:34+00:00",
      "dateModified": "2018-11-26T16:33:34+00:00",
      "description": "River Plate hooligans are blamed for an attack on the Boca Juniors bus before the Copa Libertadores final second leg.",
      "shortTitle": "River Plate \u0027mafia\u0027 blamed for attack",
      "title": "Copa Libertadores: River Plate \u0027mafia\u0027 blamed for Boca Juniors bus attack",
      "category": "http://www.bbc.co.uk/ontologies/applicationlogic-sport/News",
      "locator": [
        "urn:asset:16cefa1a-6575-454c-971e-3fe6dca9127a",
        "urn:bbc:cps:asset:46341666"
      ],
      "primaryFormat": "TextualFormat",
      "about": [
        {
          "@id": "http://www.bbc.co.uk/things/4063f80f-cccc-44c8-9449-5ca44e4c8592#id",
          "@type": [
            "http://data.press.net/ontology/classification/Classification",
            "http://www.bbc.co.uk/ontologies/classification/RootClassification",
            "skos:Concept",
            "Thing",
            "Theme"
          ],
          "label": "Sport",
          "preferredLabel": "Sport",
          "shortLabel": "Sport",
          "slug": "sport",
          "primaryTopicOf": [
            "http://en.wikipedia.org/wiki/Sport",
            "http://www.bbc.co.uk/sport"
          ],
          "sameAs": "http://dbpedia.org/resource/Sport"
        },
        {
          "@id": "http://www.bbc.co.uk/things/677f83fc-4aa8-422f-9a9e-685975882911#id",
          "@type": [
            "Thing",
            "Place",
            "geoname:GeoTagConcept"
          ],
          "label": "Buenos Aires",
          "preferredLabel": "Buenos Aires",
          "sameAs": "http://sws.geonames.org/3435910/"
        },
        {
          "@id": "http://www.bbc.co.uk/things/6b71918f-e3a3-4dff-ad36-c3d737605d43#id",
          "@type": [
            "Thing",
            "sport:RecurringCompetition",
            "sport:Competition"
          ],
          "label": "Copa Libertadores",
          "preferredLabel": "Copa Libertadores",
          "shortLabel": "Copa Libertadores",
          "slug": "copa-libertadores",
          "sameAs": "http://dbpedia.org/resource/Copa_Libertadores",
          "primaryTopicOf": [
            {
              "@id": "http://www.bbc.co.uk/sport/football/copa-libertadores",
              "webDocumentCategory": "http://www.bbc.co.uk/ontologies/applicationlogic-sport/Index"
            }
          ]
        },
        {
          "@id": "http://www.bbc.co.uk/things/ba6e1118-f874-054e-b159-b797c16e9250#id",
          "@type": [
            "Thing",
            "sport:SportsDiscipline",
            "http://www.bbc.co.uk/ontologies/applicationlogic-sport/SportTopic",
            "Theme"
          ],
          "label": [
            "Football",
            "Football"
          ],
          "preferredLabel": "Football",
          "shortLabel": "Football",
          "slug": "football",
          "primaryTopicOf": [
            "http://en.wikipedia.org/wiki/Association_football",
            "http://www.bbc.co.uk/sport/football",
            "http://www.fifa.com/",
            {
              "@id": "http://www.faw.org.uk/",
              "webDocumentCategory": "http://www.bbc.co.uk/ontologies/applicationlogic-sport/ExternalWebsite"
            },
            {
              "@id": "http://www.irishfa.com/",
              "webDocumentCategory": "http://www.bbc.co.uk/ontologies/applicationlogic-sport/ExternalWebsite"
            },
            {
              "@id": "http://www.scottishfa.co.uk/",
              "webDocumentCategory": "http://www.bbc.co.uk/ontologies/applicationlogic-sport/ExternalWebsite"
            },
            {
              "@id": "http://www.thefa.com/",
              "webDocumentCategory": "http://www.bbc.co.uk/ontologies/applicationlogic-sport/ExternalWebsite"
            }
          ],
          "sameAs": "http://dbpedia.org/resource/Association_football"
        }
      ],
      "primaryContentOf": [
        {
          "@id": "http://www.bbc.co.uk/sport/football/46341666",
          "platform": "HighWeb",
          "webDocumentType": "HighWeb"
        }
      ],
      "thumbnail": [
        {
          "@id": "http://c.files.bbci.co.uk/D726/production/_104487055_river_getty.jpg",
          "@type": [
            "Thumbnail"
          ],
          "altText": "River Plate",
          "thumbnailType": "StandardThumbnail"
        }
      ]
    },
    {
      "@id": "http://www.bbc.co.uk/things/48f29e2c-113b-4840-af13-5c05d4f7e483#id",
      "@type": [
        "CreativeWork",
        "NewsItem"
      ],
      "dateCreated": "2018-11-25T23:06:21+00:00",
      "dateModified": "2018-11-25T23:06:21+00:00",
      "description": "It was to be the biggest match in the world - but after River Plate fans attacked the Boca Juniors bus, the postponed Copa Libertadores final has shamed Argentina, writes Mani Djazmi.",
      "shortTitle": "The 36 hours that shamed Argentine football",
      "title": "Copa Libertadores: The 36 hours that shamed Argentine football",
      "category": "http://www.bbc.co.uk/ontologies/applicationlogic-sport/News",
      "locator": [
        "urn:asset:a3e58e1b-43b0-984e-870f-c72c94da348b",
        "urn:bbc:cps:asset:46337788"
      ],
      "primaryFormat": "TextualFormat",
      "about": [
        {
          "@id": "http://www.bbc.co.uk/things/4063f80f-cccc-44c8-9449-5ca44e4c8592#id",
          "@type": [
            "http://data.press.net/ontology/classification/Classification",
            "http://www.bbc.co.uk/ontologies/classification/RootClassification",
            "skos:Concept",
            "Thing",
            "Theme"
          ],
          "label": "Sport",
          "preferredLabel": "Sport",
          "shortLabel": "Sport",
          "slug": "sport",
          "primaryTopicOf": [
            "http://en.wikipedia.org/wiki/Sport",
            "http://www.bbc.co.uk/sport"
          ],
          "sameAs": "http://dbpedia.org/resource/Sport"
        },
        {
          "@id": "http://www.bbc.co.uk/things/677f83fc-4aa8-422f-9a9e-685975882911#id",
          "@type": [
            "Thing",
            "Place",
            "geoname:GeoTagConcept"
          ],
          "label": "Buenos Aires",
          "preferredLabel": "Buenos Aires",
          "sameAs": "http://sws.geonames.org/3435910/"
        },
        {
          "@id": "http://www.bbc.co.uk/things/6b71918f-e3a3-4dff-ad36-c3d737605d43#id",
          "@type": [
            "Thing",
            "sport:RecurringCompetition",
            "sport:Competition"
          ],
          "label": "Copa Libertadores",
          "preferredLabel": "Copa Libertadores",
          "shortLabel": "Copa Libertadores",
          "slug": "copa-libertadores",
          "sameAs": "http://dbpedia.org/resource/Copa_Libertadores",
          "primaryTopicOf": [
            {
              "@id": "http://www.bbc.co.uk/sport/football/copa-libertadores",
              "webDocumentCategory": "http://www.bbc.co.uk/ontologies/applicationlogic-sport/Index"
            }
          ]
        },
        {
          "@id": "http://www.bbc.co.uk/things/ba6e1118-f874-054e-b159-b797c16e9250#id",
          "@type": [
            "Thing",
            "sport:SportsDiscipline",
            "http://www.bbc.co.uk/ontologies/applicationlogic-sport/SportTopic",
            "Theme"
          ],
          "label": [
            "Football",
            "Football"
          ],
          "preferredLabel": "Football",
          "shortLabel": "Football",
          "slug": "football",
          "primaryTopicOf": [
            "http://en.wikipedia.org/wiki/Association_football",
            "http://www.bbc.co.uk/sport/football",
            "http://www.fifa.com/",
            {
              "@id": "http://www.faw.org.uk/",
              "webDocumentCategory": "http://www.bbc.co.uk/ontologies/applicationlogic-sport/ExternalWebsite"
            },
            {
              "@id": "http://www.irishfa.com/",
              "webDocumentCategory": "http://www.bbc.co.uk/ontologies/applicationlogic-sport/ExternalWebsite"
            },
            {
              "@id": "http://www.scottishfa.co.uk/",
              "webDocumentCategory": "http://www.bbc.co.uk/ontologies/applicationlogic-sport/ExternalWebsite"
            },
            {
              "@id": "http://www.thefa.com/",
              "webDocumentCategory": "http://www.bbc.co.uk/ontologies/applicationlogic-sport/ExternalWebsite"
            }
          ],
          "sameAs": "http://dbpedia.org/resource/Association_football"
        }
      ],
      "primaryContentOf": [
        {
          "@id": "http://www.bbc.co.uk/sport/football/46337788",
          "platform": "HighWeb",
          "webDocumentType": "HighWeb"
        }
      ],
      "thumbnail": [
        {
          "@id": "http://c.files.bbci.co.uk/1E9E/production/_104483870_hi050800640.jpg",
          "@type": [
            "Thumbnail"
          ],
          "altText": "A River Plate fan sets a Boca Juniors shirt alight",
          "thumbnailType": "StandardThumbnail"
        }
      ]
    },
    {
      "@id": "http://www.bbc.co.uk/things/cd05de2c-9d20-4cf7-8f4d-d5a32d8df980#id",
      "@type": [
        "CreativeWork",
        "NewsItem"
      ],
      "dateCreated": "2018-11-25T17:35:58+00:00",
      "dateModified": "2018-11-25T17:35:58+00:00",
      "description": "Sunday\u0027s Copa Libertadores final second leg between Boca Juniors and River Plate, rescheduled after violence on Saturday, is postponed.",
      "shortTitle": "Copa Libertadores final postponed again",
      "title": "Copa Libertadores: Boca Juniors against River Plate match postponed again",
      "category": "http://www.bbc.co.uk/ontologies/applicationlogic-sport/News",
      "locator": [
        "urn:asset:f4c2009a-5fdb-cf49-93ca-b87af8951d6f",
        "urn:bbc:cps:asset:46337277"
      ],
      "primaryFormat": "TextualFormat",
      "about": [
        {
          "@id": "http://www.bbc.co.uk/things/4063f80f-cccc-44c8-9449-5ca44e4c8592#id",
          "@type": [
            "http://data.press.net/ontology/classification/Classification",
            "http://www.bbc.co.uk/ontologies/classification/RootClassification",
            "skos:Concept",
            "Thing",
            "Theme"
          ],
          "label": "Sport",
          "preferredLabel": "Sport",
          "shortLabel": "Sport",
          "slug": "sport",
          "primaryTopicOf": [
            "http://en.wikipedia.org/wiki/Sport",
            "http://www.bbc.co.uk/sport"
          ],
          "sameAs": "http://dbpedia.org/resource/Sport"
        },
        {
          "@id": "http://www.bbc.co.uk/things/677f83fc-4aa8-422f-9a9e-685975882911#id",
          "@type": [
            "Thing",
            "Place",
            "geoname:GeoTagConcept"
          ],
          "label": "Buenos Aires",
          "preferredLabel": "Buenos Aires",
          "sameAs": "http://sws.geonames.org/3435910/"
        },
        {
          "@id": "http://www.bbc.co.uk/things/6b71918f-e3a3-4dff-ad36-c3d737605d43#id",
          "@type": [
            "Thing",
            "sport:RecurringCompetition",
            "sport:Competition"
          ],
          "label": "Copa Libertadores",
          "preferredLabel": "Copa Libertadores",
          "shortLabel": "Copa Libertadores",
          "slug": "copa-libertadores",
          "sameAs": "http://dbpedia.org/resource/Copa_Libertadores",
          "primaryTopicOf": [
            {
              "@id": "http://www.bbc.co.uk/sport/football/copa-libertadores",
              "webDocumentCategory": "http://www.bbc.co.uk/ontologies/applicationlogic-sport/Index"
            }
          ]
        },
        {
          "@id": "http://www.bbc.co.uk/things/ba6e1118-f874-054e-b159-b797c16e9250#id",
          "@type": [
            "Thing",
            "sport:SportsDiscipline",
            "http://www.bbc.co.uk/ontologies/applicationlogic-sport/SportTopic",
            "Theme"
          ],
          "label": [
            "Football",
            "Football"
          ],
          "preferredLabel": "Football",
          "shortLabel": "Football",
          "slug": "football",
          "primaryTopicOf": [
            "http://en.wikipedia.org/wiki/Association_football",
            "http://www.bbc.co.uk/sport/football",
            "http://www.fifa.com/",
            {
              "@id": "http://www.faw.org.uk/",
              "webDocumentCategory": "http://www.bbc.co.uk/ontologies/applicationlogic-sport/ExternalWebsite"
            },
            {
              "@id": "http://www.irishfa.com/",
              "webDocumentCategory": "http://www.bbc.co.uk/ontologies/applicationlogic-sport/ExternalWebsite"
            },
            {
              "@id": "http://www.scottishfa.co.uk/",
              "webDocumentCategory": "http://www.bbc.co.uk/ontologies/applicationlogic-sport/ExternalWebsite"
            },
            {
              "@id": "http://www.thefa.com/",
              "webDocumentCategory": "http://www.bbc.co.uk/ontologies/applicationlogic-sport/ExternalWebsite"
            }
          ],
          "sameAs": "http://dbpedia.org/resource/Association_football"
        }
      ],
      "primaryContentOf": [
        {
          "@id": "http://www.bbc.co.uk/sport/football/46337277",
          "platform": "HighWeb",
          "webDocumentType": "HighWeb"
        }
      ],
      "thumbnail": [
        {
          "@id": "http://c.files.bbci.co.uk/13004/production/_104482877_boca3.jpg",
          "@type": [
            "Thumbnail"
          ],
          "altText": "Police outside the River Plate stadium",
          "thumbnailType": "StandardThumbnail"
        }
      ]
    },
    {
      "@id": "http://www.bbc.co.uk/things/a60abe3b-db50-47c0-a6ed-9adbc079aa9c#id",
      "@type": [
        "NewsItem",
        "CreativeWork"
      ],
      "dateCreated": "2018-11-25T06:46:43+00:00",
      "dateModified": "2018-11-25T06:46:43+00:00",
      "description": "The second leg of the Copa Libertadores final is postponed for 24 hours until Sunday after River Plate fans attack the Boca Juniors team bus.",
      "shortTitle": "Copa final postponed after bus attack",
      "title": "River Plate v Boca Juniors Copa Libertadores final postponed after bus attack",
      "category": "http://www.bbc.co.uk/ontologies/applicationlogic-sport/News",
      "locator": [
        "urn:asset:1539ef1a-9dfa-ee48-b2c2-61f79be8d453",
        "urn:bbc:cps:asset:46332084"
      ],
      "primaryFormat": "TextualFormat",
      "about": [
        {
          "@id": "http://www.bbc.co.uk/things/677f83fc-4aa8-422f-9a9e-685975882911#id",
          "@type": [
            "Thing",
            "Place",
            "geoname:GeoTagConcept"
          ],
          "label": "Buenos Aires",
          "preferredLabel": "Buenos Aires",
          "sameAs": "http://sws.geonames.org/3435910/"
        },
        {
          "@id": "http://www.bbc.co.uk/things/6b71918f-e3a3-4dff-ad36-c3d737605d43#id",
          "@type": [
            "Thing",
            "sport:RecurringCompetition",
            "sport:Competition"
          ],
          "label": "Copa Libertadores",
          "preferredLabel": "Copa Libertadores",
          "shortLabel": "Copa Libertadores",
          "slug": "copa-libertadores",
          "sameAs": "http://dbpedia.org/resource/Copa_Libertadores",
          "primaryTopicOf": [
            {
              "@id": "http://www.bbc.co.uk/sport/football/copa-libertadores",
              "webDocumentCategory": "http://www.bbc.co.uk/ontologies/applicationlogic-sport/Index"
            }
          ]
        },
        {
          "@id": "http://www.bbc.co.uk/things/ba6e1118-f874-054e-b159-b797c16e9250#id",
          "@type": [
            "Thing",
            "sport:SportsDiscipline",
            "http://www.bbc.co.uk/ontologies/applicationlogic-sport/SportTopic",
            "Theme"
          ],
          "label": [
            "Football",
            "Football"
          ],
          "preferredLabel": "Football",
          "shortLabel": "Football",
          "slug": "football",
          "primaryTopicOf": [
            "http://en.wikipedia.org/wiki/Association_football",
            "http://www.bbc.co.uk/sport/football",
            "http://www.fifa.com/",
            {
              "@id": "http://www.faw.org.uk/",
              "webDocumentCategory": "http://www.bbc.co.uk/ontologies/applicationlogic-sport/ExternalWebsite"
            },
            {
              "@id": "http://www.irishfa.com/",
              "webDocumentCategory": "http://www.bbc.co.uk/ontologies/applicationlogic-sport/ExternalWebsite"
            },
            {
              "@id": "http://www.scottishfa.co.uk/",
              "webDocumentCategory": "http://www.bbc.co.uk/ontologies/applicationlogic-sport/ExternalWebsite"
            },
            {
              "@id": "http://www.thefa.com/",
              "webDocumentCategory": "http://www.bbc.co.uk/ontologies/applicationlogic-sport/ExternalWebsite"
            }
          ],
          "sameAs": "http://dbpedia.org/resource/Association_football"
        }
      ],
      "primaryContentOf": [
        {
          "@id": "http://www.bbc.co.uk/sport/football/46332084",
          "platform": "HighWeb",
          "webDocumentType": "HighWeb"
        }
      ],
      "thumbnail": [
        {
          "@id": "http://c.files.bbci.co.uk/C0CD/production/_104475394_hi050794959.jpg",
          "@type": [
            "Thumbnail"
          ],
          "altText": "The Boca Juniors team bus ahead of the Copa Libertadores final second leg.",
          "thumbnailType": "StandardThumbnail"
        }
      ]
    },
    {
      "@id": "http://www.bbc.co.uk/things/cf75d49d-11ab-4762-9a97-9ea703068faf#id",
      "@type": [
        "NewsItem",
        "CreativeWork"
      ],
      "dateCreated": "2018-11-25T02:40:52+00:00",
      "dateModified": "2018-11-25T02:40:52+00:00",
      "description": "Clashes between Boca Juniors and River Plate have injured players and delayed the Copa Libertadores final.",
      "shortTitle": "Football final postponed after team bus attack",
      "title": "Boca Juniors v River Plate final in Copa Libertadores postponed after team bus attacked.",
      "category": "http://www.bbc.co.uk/ontologies/applicationlogic-news/News",
      "locator": [
        "urn:asset:d74b9e62-e0bc-3947-82da-016fbaa0f344",
        "urn:bbc:cps:asset:46332745"
      ],
      "primaryFormat": "VideoFormat",
      "about": [
        {
          "@id": "http://www.bbc.co.uk/things/677f83fc-4aa8-422f-9a9e-685975882911#id",
          "@type": [
            "Thing",
            "Place",
            "geoname:GeoTagConcept"
          ],
          "label": "Buenos Aires",
          "preferredLabel": "Buenos Aires",
          "sameAs": "http://sws.geonames.org/3435910/"
        },
        {
          "@id": "http://www.bbc.co.uk/things/6b71918f-e3a3-4dff-ad36-c3d737605d43#id",
          "@type": [
            "Thing",
            "sport:RecurringCompetition",
            "sport:Competition"
          ],
          "label": "Copa Libertadores",
          "preferredLabel": "Copa Libertadores",
          "shortLabel": "Copa Libertadores",
          "slug": "copa-libertadores",
          "sameAs": "http://dbpedia.org/resource/Copa_Libertadores",
          "primaryTopicOf": [
            {
              "@id": "http://www.bbc.co.uk/sport/football/copa-libertadores",
              "webDocumentCategory": "http://www.bbc.co.uk/ontologies/applicationlogic-sport/Index"
            }
          ]
        },
        {
          "@id": "http://www.bbc.co.uk/things/ba6e1118-f874-054e-b159-b797c16e9250#id",
          "@type": [
            "Thing",
            "sport:SportsDiscipline",
            "http://www.bbc.co.uk/ontologies/applicationlogic-sport/SportTopic",
            "Theme"
          ],
          "label": [
            "Football",
            "Football"
          ],
          "preferredLabel": "Football",
          "shortLabel": "Football",
          "slug": "football",
          "primaryTopicOf": [
            "http://en.wikipedia.org/wiki/Association_football",
            "http://www.bbc.co.uk/sport/football",
            "http://www.fifa.com/",
            {
              "@id": "http://www.faw.org.uk/",
              "webDocumentCategory": "http://www.bbc.co.uk/ontologies/applicationlogic-sport/ExternalWebsite"
            },
            {
              "@id": "http://www.irishfa.com/",
              "webDocumentCategory": "http://www.bbc.co.uk/ontologies/applicationlogic-sport/ExternalWebsite"
            },
            {
              "@id": "http://www.scottishfa.co.uk/",
              "webDocumentCategory": "http://www.bbc.co.uk/ontologies/applicationlogic-sport/ExternalWebsite"
            },
            {
              "@id": "http://www.thefa.com/",
              "webDocumentCategory": "http://www.bbc.co.uk/ontologies/applicationlogic-sport/ExternalWebsite"
            }
          ],
          "sameAs": "http://dbpedia.org/resource/Association_football"
        },
        {
          "@id": "http://www.bbc.co.uk/things/f0e68d01-22ae-42a7-9e05-d299a29d4ce5#id",
          "@type": [
            "Thing",
            "Place",
            "geoname:GeoTagConcept"
          ],
          "label": "Argentina",
          "preferredLabel": "Argentina",
          "sameAs": "http://sws.geonames.org/3865483/"
        }
      ],
      "primaryContentOf": [
        {
          "@id": "http://www.bbc.co.uk/news/world-latin-america-46332745",
          "platform": "HighWeb",
          "webDocumentType": "HighWeb"
        }
      ],
      "thumbnail": [
        {
          "@id": "http://c.files.bbci.co.uk/1079F/production/_104478476_p06sskfm.jpg",
          "@type": [
            "Thumbnail"
          ],
          "altText": "Injured player",
          "thumbnailType": "StandardThumbnail"
        }
      ]
    }
  ],
  "@context": {
    "CreativeWork": {
      "@id": "http://www.bbc.co.uk/ontologies/creativework/CreativeWork"
    },
    "HighWeb": {
      "@id": "http://www.bbc.co.uk/ontologies/bbc/HighWeb"
    },
    "LiveCoverage": {
      "@id": "http://www.bbc.co.uk/ontologies/creativework/LiveCoverage"
    },
    "NewsItem": {
      "@id": "http://www.bbc.co.uk/ontologies/creativework/NewsItem"
    },
    "Place": {
      "@id": "http://www.bbc.co.uk/ontologies/coreconcepts/Place"
    },
    "StandardThumbnail": {
      "@id": "http://www.bbc.co.uk/ontologies/creativework/StandardThumbnail"
    },
    "TextualFormat": {
      "@id": "http://www.bbc.co.uk/ontologies/creativework/TextualFormat"
    },
    "Theme": {
      "@id": "http://www.bbc.co.uk/ontologies/coreconcepts/Theme"
    },
    "Thing": {
      "@id": "http://www.bbc.co.uk/ontologies/coreconcepts/Thing"
    },
    "Thumbnail": {
      "@id": "http://www.bbc.co.uk/ontologies/creativework/Thumbnail"
    },
    "VideoFormat": {
      "@id": "http://www.bbc.co.uk/ontologies/creativework/VideoFormat"
    },
    "about": {
      "@id": "http://www.bbc.co.uk/ontologies/creativework/about",
      "@type": "@id"
    },
    "altText": {
      "@id": "http://www.bbc.co.uk/ontologies/creativework/altText"
    },
    "category": {
      "@id": "http://www.bbc.co.uk/ontologies/creativework/category",
      "@type": "@id"
    },
    "dateCreated": {
      "@id": "http://www.bbc.co.uk/ontologies/creativework/dateCreated"
    },
    "dateModified": {
      "@id": "http://www.bbc.co.uk/ontologies/creativework/dateModified"
    },
    "description": {
      "@id": "http://www.bbc.co.uk/ontologies/creativework/description"
    },
    "geoname:GeoTagConcept": {
      "@id": "http://www.geonames.org/ontology#GeoTagConcept"
    },
    "label": {
      "@id": "http://www.w3.org/2000/01/rdf-schema#label"
    },
    "locator": {
      "@id": "http://www.bbc.co.uk/ontologies/cms/locator",
      "@type": "@id"
    },
    "platform": {
      "@id": "http://www.bbc.co.uk/ontologies/bbc/platform",
      "@type": "@vocab"
    },
    "preferredLabel": {
      "@id": "http://www.bbc.co.uk/ontologies/coreconcepts/preferredLabel"
    },
    "primaryContentOf": {
      "@id": "http://www.bbc.co.uk/ontologies/bbc/primaryContentOf",
      "@type": "@id"
    },
    "primaryFormat": {
      "@id": "http://www.bbc.co.uk/ontologies/creativework/primaryFormat",
      "@type": "@vocab"
    },
    "primaryTopicOf": {
      "@id": "http://www.bbc.co.uk/ontologies/coreconcepts/primaryTopicOf",
      "@type": "@id"
    },
    "results": {
      "@id": "@graph"
    },
    "sameAs": {
      "@id": "http://www.bbc.co.uk/ontologies/coreconcepts/sameAs",
      "@type": "@id"
    },
    "shortLabel": {
      "@id": "http://www.bbc.co.uk/ontologies/coreconcepts/shortLabel"
    },
    "shortTitle": {
      "@id": "http://www.bbc.co.uk/ontologies/creativework/shortTitle"
    },
    "skos:Concept": {
      "@id": "http://www.w3.org/2004/02/skos/core#Concept"
    },
    "slug": {
      "@id": "http://www.bbc.co.uk/ontologies/coreconcepts/slug"
    },
    "sport:Competition": {
      "@id": "http://www.bbc.co.uk/ontologies/sport/Competition"
    },
    "sport:RecurringCompetition": {
      "@id": "http://www.bbc.co.uk/ontologies/sport/RecurringCompetition"
    },
    "sport:SportsDiscipline": {
      "@id": "http://www.bbc.co.uk/ontologies/sport/SportsDiscipline"
    },
    "thumbnail": {
      "@id": "http://www.bbc.co.uk/ontologies/creativework/thumbnail",
      "@type": "@id"
    },
    "thumbnailType": {
      "@id": "http://www.bbc.co.uk/ontologies/creativework/thumbnailType",
      "@type": "@vocab"
    },
    "title": {
      "@id": "http://www.bbc.co.uk/ontologies/creativework/title"
    },
    "type": {
      "@id": "http://www.w3.org/1999/02/22-rdf-syntax-ns#type",
      "@type": "@vocab"
    },
    "webDocumentCategory": {
      "@id": "http://www.bbc.co.uk/ontologies/bbc/webDocumentCategory",
      "@type": "@id"
    },
    "webDocumentType": {
      "@id": "http://www.bbc.co.uk/ontologies/bbc/webDocumentType",
      "@type": "@vocab"
    }
  }
}